{
  "update_time": "2026-02-26 14:44:16",
  "total": 70,
  "news": [
    {
      "title": "將 NotebookLM 快速批次轉成 PPT 之法",
      "link": "https://www.newmobilelife.com/2026/02/25/notebooklm-to-ppt-batch/",
      "source": "NewMobileLife",
      "category": "科技",
      "scraped_at": "2026-02-26 14:44:14"
    },
    {
      "title": "Apple 預計發佈至少五款新品　迎接 3 月 4 日活動",
      "link": "https://www.newmobilelife.com/2026/02/22/apple-event-march-five-new-products/",
      "source": "NewMobileLife",
      "category": "科技",
      "scraped_at": "2026-02-26 14:44:14"
    },
    {
      "title": "今年最大折扣　Parallels Desktop 26 限時 55 折",
      "link": "https://www.newmobilelife.com/2026/02/24/parallels-desktop-26-feb-26-discount/",
      "source": "NewMobileLife",
      "category": "科技",
      "scraped_at": "2026-02-26 14:44:14"
    },
    {
      "title": "Apple 預計 3 月 4 日發佈廉價版 MacBook　多款鮮艷配色同步登場",
      "link": "https://www.newmobilelife.com/2026/02/18/apple-cheap-macbook-march-launch/",
      "source": "NewMobileLife",
      "category": "科技",
      "scraped_at": "2026-02-26 14:44:14"
    },
    {
      "title": "iOS 26.4 Beta 1 正式推出　大量新功能全面看",
      "link": "https://www.newmobilelife.com/2026/02/17/ios-26-4-beta-app-features/",
      "source": "NewMobileLife",
      "category": "科技",
      "scraped_at": "2026-02-26 14:44:14"
    },
    {
      "title": "Samsung 發佈 Galaxy S26 系列　首創隱私螢幕與深度 AI 整合功能",
      "link": "https://www.newmobilelife.com/2026/02/26/samsung-galaxy-s26-whatsnew/",
      "source": "NewMobileLife",
      "category": "科技",
      "scraped_at": "2026-02-26 14:44:14"
    },
    {
      "title": "macOS 27 新功能傳聞　介面或為觸控作優化",
      "link": "https://www.newmobilelife.com/2026/02/26/macos-27-rumors-2026-wwdc/",
      "source": "NewMobileLife",
      "category": "科技",
      "scraped_at": "2026-02-26 14:44:14"
    },
    {
      "title": "全新 AI 代理系統 Perplexity Computer 發佈　整合多款頂尖模型實現自動化工作流",
      "link": "https://www.newmobilelife.com/2026/02/26/perplexity-ai-agent-computer/",
      "source": "NewMobileLife",
      "category": "科技",
      "scraped_at": "2026-02-26 14:44:14"
    },
    {
      "title": "《限時情報王》iOS 版大更新　全面支援 iOS 26 Liquid Glass UI",
      "link": "https://www.newmobilelife.com/2026/02/14/%e9%99%90%e6%99%82%e6%83%85%e5%a0%b1%e7%8e%8b-1-4/",
      "source": "NewMobileLife",
      "category": "科技",
      "scraped_at": "2026-02-26 14:44:14"
    },
    {
      "title": "我們的新 App《名言金句》上架了！首發限時免費中（無廣告）！",
      "link": "https://www.newmobilelife.com/2026/02/13/%e9%87%91%e5%8f%a5%e5%90%8d%e8%a8%80-ios-app/",
      "source": "NewMobileLife",
      "category": "科技",
      "scraped_at": "2026-02-26 14:44:14"
    },
    {
      "title": "iOS 26.3 及 iPadOS 26.3 正式版登場　新功能一覽",
      "link": "https://www.newmobilelife.com/2026/02/12/apple-ios-ipados-26-3-whatsnew/",
      "source": "NewMobileLife",
      "category": "科技",
      "scraped_at": "2026-02-26 14:44:14"
    },
    {
      "title": "AirTag 2 評測　追蹤距離與音量顯著提升",
      "link": "https://www.newmobilelife.com/2026/02/03/apple-airtag-2-review-range-volume/",
      "source": "NewMobileLife",
      "category": "科技",
      "scraped_at": "2026-02-26 14:44:14"
    },
    {
      "title": "Google One Premium 2TB 用戶新福利　免費自動獲得 Google AI Plus 權益",
      "link": "https://www.newmobilelife.com/2026/01/29/google-one-premium-2tb-free-google-ai-plus/",
      "source": "NewMobileLife",
      "category": "科技",
      "scraped_at": "2026-02-26 14:44:14"
    },
    {
      "title": "中文語音輸入自動生成待辦清單　原價 US $49.99《To-Do Speak AI》終生版限時免費",
      "link": "https://www.newmobilelife.com/2026/02/25/to-do-speak-ai-%e9%99%90%e6%99%82%e5%85%8d%e8%b2%bb-2/",
      "source": "NewMobileLife",
      "category": "科技",
      "scraped_at": "2026-02-26 14:44:14"
    },
    {
      "title": "極簡美觀習慣追蹤　原價 US $2.99《Habit Tracker Widget》限時免費",
      "link": "https://www.newmobilelife.com/2026/02/24/habit-tracker-widget-%e9%99%90%e6%99%82%e5%85%8d%e8%b2%bb-2/",
      "source": "NewMobileLife",
      "category": "科技",
      "scraped_at": "2026-02-26 14:44:14"
    },
    {
      "title": "國泰飛曼谷！連稅二千一起！4月30日前出發！香港飛曼谷來回連稅只需$2,175起 – 國泰航空 (優惠至3月9日)",
      "link": "https://www.meethk.com/158264/",
      "source": "MeetHK",
      "category": "旅遊",
      "scraped_at": "2026-02-26 14:44:14"
    },
    {
      "title": "平到笑！達美直飛洛杉磯！連稅4千2！6月27日前出發！香港直飛洛杉磯來回連稅只需$4,262起 – 達美航空 (優惠至3月20日)",
      "link": "https://www.meethk.com/158272/",
      "source": "MeetHK",
      "category": "旅遊",
      "scraped_at": "2026-02-26 14:44:14"
    },
    {
      "title": "國泰飛日本再減！連稅2千6起！6月30日前出發！香港飛東京/大阪/福岡/名古屋連稅$2,658起 – 國泰航空 (優惠至3月9日)",
      "link": "https://www.meethk.com/158210/",
      "source": "MeetHK",
      "category": "旅遊",
      "scraped_at": "2026-02-26 14:44:14"
    },
    {
      "title": "國泰飛札幌再減！連稅3千5起！6月30日前出發！香港飛札幌連稅只需$3,554起 – 國泰航空 (優惠至3月9日)",
      "link": "https://www.meethk.com/158215/",
      "source": "MeetHK",
      "category": "旅遊",
      "scraped_at": "2026-02-26 14:44:14"
    },
    {
      "title": "EastarJet開賣啦！飛首爾連稅千一起！包15kg寄艙行李！凌晨機去晚機返！香港飛首爾來回連稅只需$1,169起 – EastarJet 易斯達航空",
      "link": "https://www.meethk.com/158145/",
      "source": "MeetHK",
      "category": "旅遊",
      "scraped_at": "2026-02-26 14:44:14"
    },
    {
      "title": "嘩！AirAsia全線機票低至0.1折！連稅八百飛沖繩！仲有一蚊飛沙巴(亞庇)、$15飛曼谷(廊曼)、澳門飛曼谷(廊曼)$0！6月至明年3月27日前出發！訂飛時同時加購Value Pack仲有高達9折優惠 – AirAsia (優惠至3月1日)",
      "link": "https://www.meethk.com/158014/",
      "source": "MeetHK",
      "category": "旅遊",
      "scraped_at": "2026-02-26 14:44:14"
    },
    {
      "title": "$218飛仙台/廣島/高松！日本限時優惠！7月12日前出發！香港飛仙台/廣島/高松單程只需$218起 – HK Express (優惠至2月22日)",
      "link": "https://www.meethk.com/158121/",
      "source": "MeetHK",
      "category": "旅遊",
      "scraped_at": "2026-02-26 14:44:14"
    },
    {
      "title": "嘩！激抵呀！連稅千九飛札幌！包20kg寄艙行李！7月8日前出發！香港飛札幌來回連稅只需$1,933起 – 大灣區航空",
      "link": "https://www.meethk.com/158126/",
      "source": "MeetHK",
      "category": "旅遊",
      "scraped_at": "2026-02-26 14:44:14"
    },
    {
      "title": "美食推介．主題特集．【JetsoWong著數王】【自助餐優惠】城景國際酒店半價自助餐！午餐最平$208起 晚餐任食生蠔蟹腳／泰式沙爹串燒（附預訂詳情）城景國際由即日起推出自助餐優惠，午餐低至51折，每位最平$208起就食到！3月更將推出「味遊東南亞‧...a minute ago",
      "link": "https://holidaysmart.io/hk/article/468552/%E8%87%AA%E5%8A%A9%E9%A4%90%E5%84%AA%E6%83%A0-%E5%9F%8E%E6%99%AF%E5%9C%8B%E9%9A%9B%E9%85%92%E5%BA%97%E5%8D%8A%E5%83%B9%E8%87%AA%E5%8A%A9%E9%A4%90-%E9%A0%90%E8%A8%82",
      "source": "HolidaySmart",
      "category": "旅遊",
      "scraped_at": "2026-02-26 14:44:15"
    },
    {
      "title": "主題特集．【JetsoWong著數王】【香港快運優惠】1＋1飛行套票回歸！低至$648入手兩套來回機票  東京／首爾／台北／曼谷港人最愛就係去旅行衝上雲霄！ 香港快運 嚟到馬年亦推出快閃驚喜優惠，宣布「香港快運 飛行套票」回歸～即日起入指定網頁預訂...a day ago",
      "link": "https://holidaysmart.io/hk/article/468518/%E9%A6%99%E6%B8%AF%E5%BF%AB%E9%81%8B%E5%84%AA%E6%83%A0-1%EF%BC%8B1%E9%A3%9B%E8%A1%8C%E5%A5%97%E7%A5%A8%E5%9B%9E%E6%AD%B8",
      "source": "HolidaySmart",
      "category": "旅遊",
      "scraped_at": "2026-02-26 14:44:15"
    },
    {
      "title": "美食推介【DONKI 必買清單2026】12款無限回購好物：薄朱雪糕＋芝士粒每次走入 DONKI ，看到琳瑯滿目的黃色貨架就會讓人患上選擇困難症！小編整理了網民極力推薦以及編輯私心珍藏的香港DON...a day ago",
      "link": "https://holidaysmart.io/hk/article/468473/donki-%E5%BF%85%E8%B2%B7%E6%B8%85%E5%96%AE",
      "source": "HolidaySmart",
      "category": "旅遊",
      "scraped_at": "2026-02-26 14:44:15"
    },
    {
      "title": "美食推介【MBTI開運飯指南】E人熱鬧圍爐 vs I人精緻放閃 5大餐廳助你馬年食出好運氣！講到過年，最緊要梗係「食得開懷」啦！不過每年搵開年飯Gathering諗到頭都大埋？今年不如試吓搞搞...14 days ago",
      "link": "https://holidaysmart.io/hk/article/468364/%E3%80%90mbti%E9%96%8B%E9%81%8B%E9%A3%AF%E6%8C%87%E5%8D%97%E3%80%91e%E4%BA%BA%E7%86%B1%E9%AC%A7%E5%9C%8D%E7%88%90-vs-i%E4%BA%BA%E7%B2%BE%E7%B7%BB%E6%94%BE%E9%96%83-5%E5%A4%A7%E9%A4%90%E5%BB%B3",
      "source": "HolidaySmart",
      "category": "旅遊",
      "scraped_at": "2026-02-26 14:44:15"
    },
    {
      "title": "電視電影【賀歲片2026】香港5部必睇新年電影｜夜王、鏢人、金多寶 附預告＋上映時間＋劇情簡介賀歲片2026｜香港5部必睇新年電影推介：黃子華鄭秀文《夜王》、李連杰復出《鏢人》、《金多寶》、《驚...15 days ago",
      "link": "https://holidaysmart.io/hk/article/445962/%E8%B3%80%E6%AD%B2%E7%89%87",
      "source": "HolidaySmart",
      "category": "旅遊",
      "scraped_at": "2026-02-26 14:44:15"
    },
    {
      "title": "香港好去處．購物著數【年宵花市2026】全港14大年宵市場懶人包：維園年宵開放時間／交通／實時人流追蹤2026農曆新年將至，逛年宵花市是香港人必備的過年儀式感！年宵花市2026將於2月11日（年廿四）起一連七日盛大舉行！今...16 days ago",
      "link": "https://holidaysmart.io/hk/article/468235/%E5%B9%B4%E5%AE%B5%E8%8A%B1%E5%B8%82-%E5%B9%B4%E5%AE%B5%E5%B8%82%E5%A0%B4",
      "source": "HolidaySmart",
      "category": "旅遊",
      "scraped_at": "2026-02-26 14:44:15"
    },
    {
      "title": "旅遊新聞優惠【機場新春購物賞✈️】消費享2X積分兼享20+限定商戶優惠、憑銀聯卡獲額外高達HK$1,250現金券由即日起至2026年3月1日，HKairport Rewards會員可享一系列限定購物禮遇，等您出發...20 days ago",
      "link": "https://holidaysmart.io/hk/article/468172/%E3%80%90%E6%A9%9F%E5%A0%B4%E6%96%B0%E6%98%A5%E8%B3%BC%E7%89%A9%E8%B3%9E%E2%9C%88%EF%B8%8F%E3%80%91%E6%B6%88%E8%B2%BB%E4%BA%AB2x%E7%A9%8D%E5%88%86%E5%85%BC%E4%BA%AB20%E9%99%90%E5%AE%9A%E5%95%86",
      "source": "HolidaySmart",
      "category": "旅遊",
      "scraped_at": "2026-02-26 14:44:15"
    },
    {
      "title": "香港好去處．商場【新年好去處2026｜持續更新】20＋馬年商場打卡合集！水怪／燦子／Snoopy＋新春市集（附地點／開放時間）【新年好去處2026｜持續更新】農曆 新年 將至，馬年行大運去邊好？各大商場陸續推出新春佈置打卡位及活動，HANGYOD...20 days ago",
      "link": "https://holidaysmart.io/hk/article/467579/%E6%96%B0%E5%B9%B4%E5%A5%BD%E5%8E%BB%E8%99%952026-%E9%A6%AC%E5%B9%B4%E5%95%86%E5%A0%B4%E6%89%93%E5%8D%A1%E5%90%88%E9%9B%86",
      "source": "HolidaySmart",
      "category": "旅遊",
      "scraped_at": "2026-02-26 14:44:15"
    },
    {
      "title": "【JetsoWong著數王】【香港航空機票優惠】日本／韓國／泰國等15大航點低至85折！AlipayHK每日大派$100消費券！農曆新年 快到啦！想趁長假出遊？AlipayHK再度聯乘香港航空帶來 限時機票優惠 ，多達澳洲、加拿大、內地、東南亞等1...20 days ago",
      "link": "https://holidaysmart.io/hk/article/468138/%E6%A9%9F%E7%A5%A8%E5%84%AA%E6%83%A0-%E9%A6%99%E6%B8%AF%E8%88%AA%E7%A9%BA-%E5%84%AA%E6%83%A0%E8%91%97%E6%95%B8-%E9%99%90%E6%99%82%E5%84%AA%E6%83%A0",
      "source": "HolidaySmart",
      "category": "旅遊",
      "scraped_at": "2026-02-26 14:44:15"
    },
    {
      "title": "美食推介．購物著數【新年年糕2026】18間推介！優惠65折起：翡翠／鮑魚臘味蘿蔔糕＋黑松露芋頭糕＋金沙奶黃年糕（附價錢連結）新年年糕202626｜18間新年糕點推介～附價錢與購買連結！65折起！各大酒店、餅店及食府推出賀年糕...21 days ago",
      "link": "https://holidaysmart.io/hk/article/445250/%E6%96%B0%E5%B9%B4%E5%B9%B4%E7%B3%952026-%E8%98%BF%E8%94%94%E7%B3%95-%E8%8A%8B%E9%A0%AD%E7%B3%95-%E5%83%B9%E9%8C%A2-%E6%97%A9%E9%B3%A5%E5%84%AA%E6%83%A0",
      "source": "HolidaySmart",
      "category": "旅遊",
      "scraped_at": "2026-02-26 14:44:15"
    },
    {
      "title": "美食推介【上海炒年糕食譜】新手也能做出餐廳級美味！5步驟做法全攻略，教你炒出Q彈不黏牙口感每次去上海菜館必點的「上海炒年糕」，其實在家自製超簡單！這道料理成功的關鍵，在於年糕要保持外滑內軟、Q彈不黏牙，配上吸飽...21 days ago",
      "link": "https://holidaysmart.io/hk/article/468038/%E4%B8%8A%E6%B5%B7%E7%82%92%E5%B9%B4%E7%B3%95",
      "source": "HolidaySmart",
      "category": "旅遊",
      "scraped_at": "2026-02-26 14:44:15"
    },
    {
      "title": "美食推介【將軍澳新店優惠】人氣脆皮燒雞登場！買燒雞即送楊枝甘露！各位將軍澳街坊有福啦！灣仔人氣餐廳「薔紅宅急便」終於進駐 將軍澳 ！以金牌脆皮燒春雞打響名堂的薔紅，近年逆市擴張，全港已...22 days ago",
      "link": "https://holidaysmart.io/hk/article/468011/%E5%84%AA%E6%83%A0%E8%91%97%E6%95%B8-%E9%99%90%E6%99%82%E5%84%AA%E6%83%A0-%E6%96%B0%E5%BA%97%E5%84%AA%E6%83%A0-%E5%B0%87%E8%BB%8D%E6%BE%B3",
      "source": "HolidaySmart",
      "category": "旅遊",
      "scraped_at": "2026-02-26 14:44:15"
    },
    {
      "title": "227 Jan【將軍澳火鍋優惠】$68半價歎安格斯牛一人火鍋 + $1無限追加！",
      "link": "https://holidaysmart.io/hk/article/467597/%E6%96%B0%E5%BA%97%E5%84%AA%E6%83%A0-%E9%99%90%E6%99%82%E5%84%AA%E6%83%A0-%E5%84%AA%E6%83%A0%E8%91%97%E6%95%B8-%E7%81%AB%E9%8D%8B%E5%BA%97-%E5%B0%87%E8%BB%8D%E6%BE%B3-%E7%BE%8E%E9%A3%9F",
      "source": "HolidaySmart",
      "category": "旅遊",
      "scraped_at": "2026-02-26 14:44:15"
    },
    {
      "title": "530 Jan2026新年煙花全攻略｜維港年初二煙花13大最佳觀賞點：草地躺平、無敵廣角、隱藏地圖全收錄",
      "link": "https://holidaysmart.io/hk/article/467854/%E6%96%B0%E5%B9%B4%E7%85%99%E8%8A%B1",
      "source": "HolidaySmart",
      "category": "旅遊",
      "scraped_at": "2026-02-26 14:44:15"
    },
    {
      "title": "603 Feb【新年好去處2026】開運必到德福廣場！紅A塑膠用品藝術打卡位＋紅運新年市集",
      "link": "https://holidaysmart.io/hk/article/467905/%E6%96%B0%E5%B9%B4%E5%A5%BD%E5%8E%BB%E8%99%952026-%E5%BE%B7%E7%A6%8F%E5%BB%A3%E5%A0%B4-%E7%B4%85a",
      "source": "HolidaySmart",
      "category": "旅遊",
      "scraped_at": "2026-02-26 14:44:15"
    },
    {
      "title": "大電池未必最耐用？手機續航力排名出爐 「呢部手機」驚喜奪冠 【專家實測】",
      "link": "https://ezone.hk/article/20090054/%E5%A4%A7%E9%9B%BB%E6%B1%A0%E6%9C%AA%E5%BF%85%E6%9C%80%E8%80%90%E7%94%A8-%E6%89%8B%E6%A9%9F%E7%BA%8C%E8%88%AA%E5%8A%9B%E6%8E%92%E5%90%8D%E5%87%BA%E7%88%90-%E5%91%A2%E9%83%A8%E6%89%8B%E6%A9%9F-%E9%A9%9A%E5%96%9C%E5%A5%AA%E5%86%A0-%E5%B0%88%E5%AE%B6%E5%AF%A6%E6%B8%AC",
      "source": "E-zone",
      "category": "科技",
      "scraped_at": "2026-02-26 14:44:15"
    },
    {
      "title": "Honor Magic V6 預告 3‧1 MWC 首發 赤兔紅機身＋電量最多摺機",
      "link": "https://ezone.hk/article/20090016/Honor-Magic-V6-%E9%A0%90%E5%91%8A-3-1-MWC-%E9%A6%96%E7%99%BC-%E8%B5%A4%E5%85%94%E7%B4%85%E6%A9%9F%E8%BA%AB-%E9%9B%BB%E9%87%8F%E6%9C%80%E5%A4%9A%E6%91%BA%E6%A9%9F",
      "source": "E-zone",
      "category": "科技",
      "scraped_at": "2026-02-26 14:44:15"
    },
    {
      "title": "Samsung Unpacked 2026 隱藏驚喜！Galaxy Book6 歷來最薄 AI 筆電、Buds4 體感耳機及百變屏幕實機直擊",
      "link": "https://ezone.hk/article/20090188/Samsung-Unpacked-2026-%E9%9A%B1%E8%97%8F%E9%A9%9A%E5%96%9C-Galaxy-Book6-%E6%AD%B7%E4%BE%86%E6%9C%80%E8%96%84-AI-%E7%AD%86%E9%9B%BB-Buds4-%E9%AB%94%E6%84%9F%E8%80%B3%E6%A9%9F%E5%8F%8A%E7%99%BE%E8%AE%8A%E5%B1%8F%E5%B9%95%E5%AF%A6%E6%A9%9F%E7%9B%B4%E6%93%8A",
      "source": "E-zone",
      "category": "科技",
      "scraped_at": "2026-02-26 14:44:15"
    },
    {
      "title": "告別電動車低牌費時代 按kW分級最高$11,000，Tesla、BMW、BYD車主新開支一文看清",
      "link": "https://ezone.hk/article/20062354/%E5%91%8A%E5%88%A5%E9%9B%BB%E5%8B%95%E8%BB%8A%E4%BD%8E%E7%89%8C%E8%B2%BB%E6%99%82%E4%BB%A3-%E6%8C%89kW%E5%88%86%E7%B4%9A%E6%9C%80%E9%AB%98-11-000-Tesla-BMW-BYD%E8%BB%8A%E4%B8%BB%E6%96%B0%E9%96%8B%E6%94%AF%E4%B8%80%E6%96%87%E7%9C%8B%E6%B8%85",
      "source": "E-zone",
      "category": "科技",
      "scraped_at": "2026-02-26 14:44:15"
    },
    {
      "title": "自動駕駛測試擴區！蘿蔔快跑測試路段延至 43.2 公里　由機場至東涌及欣澳",
      "link": "https://ezone.hk/article/20090180/%E8%87%AA%E5%8B%95%E9%A7%95%E9%A7%9B%E6%B8%AC%E8%A9%A6%E6%93%B4%E5%8D%80-%E8%98%BF%E8%94%94%E5%BF%AB%E8%B7%91%E6%B8%AC%E8%A9%A6%E8%B7%AF%E6%AE%B5%E5%BB%B6%E8%87%B3-43-2-%E5%85%AC%E9%87%8C-%E7%94%B1%E6%A9%9F%E5%A0%B4%E8%87%B3%E6%9D%B1%E6%B6%8C%E5%8F%8A%E6%AC%A3%E6%BE%B3",
      "source": "E-zone",
      "category": "科技",
      "scraped_at": "2026-02-26 14:44:15"
    },
    {
      "title": "恐怖過撞鬼！iPhone「通靈」半夜自動打電話 教 2 招拆解手機陰間 Bug",
      "link": "https://ezone.hk/article/20090164/%E6%81%90%E6%80%96%E9%81%8E%E6%92%9E%E9%AC%BC-iPhone-%E9%80%9A%E9%9D%88-%E5%8D%8A%E5%A4%9C%E8%87%AA%E5%8B%95%E6%89%93%E9%9B%BB%E8%A9%B1-%E6%95%99-2-%E6%8B%9B%E6%8B%86%E8%A7%A3%E6%89%8B%E6%A9%9F%E9%99%B0%E9%96%93-Bug",
      "source": "E-zone",
      "category": "科技",
      "scraped_at": "2026-02-26 14:44:15"
    },
    {
      "title": "網民熱論電動私家車「一換一正式完結」即日訂車仲食到優惠 AION、MG、Tesla 等 Showroom 一晚限定延長營業爭生意",
      "link": "https://ezone.hk/article/20090154/%E7%B6%B2%E6%B0%91%E7%86%B1%E8%AB%96%E9%9B%BB%E5%8B%95%E7%A7%81%E5%AE%B6%E8%BB%8A-%E4%B8%80%E6%8F%9B%E4%B8%80%E6%AD%A3%E5%BC%8F%E5%AE%8C%E7%B5%90-%E5%8D%B3%E6%97%A5%E8%A8%82%E8%BB%8A%E4%BB%B2%E9%A3%9F%E5%88%B0%E5%84%AA%E6%83%A0-AION-MG-Tesla-%E7%AD%89-Showroom-%E4%B8%80%E6%99%9A%E9%99%90%E5%AE%9A%E5%BB%B6%E9%95%B7%E7%87%9F%E6%A5%AD%E7%88%AD%E7%94%9F%E6%84%8F",
      "source": "E-zone",
      "category": "科技",
      "scraped_at": "2026-02-26 14:44:15"
    },
    {
      "title": "財政預算案2026｜政府公共服務 AI 化　勞工處智能配對幫你搵工　AI 實時預測評估水浸 / 山泥傾瀉風險",
      "link": "https://ezone.hk/article/20090131/%E8%B2%A1%E6%94%BF%E9%A0%90%E7%AE%97%E6%A1%882026-%E6%94%BF%E5%BA%9C%E5%85%AC%E5%85%B1%E6%9C%8D%E5%8B%99-AI-%E5%8C%96-%E5%8B%9E%E5%B7%A5%E8%99%95%E6%99%BA%E8%83%BD%E9%85%8D%E5%B0%8D%E5%B9%AB%E4%BD%A0%E6%90%B5%E5%B7%A5-AI-%E5%AF%A6%E6%99%82%E9%A0%90%E6%B8%AC%E8%A9%95%E4%BC%B0%E6%B0%B4%E6%B5%B8-%E5%B1%B1%E6%B3%A5%E5%82%BE%E7%80%89%E9%A2%A8%E9%9A%AA",
      "source": "E-zone",
      "category": "科技",
      "scraped_at": "2026-02-26 14:44:15"
    },
    {
      "title": "財政預算案2026｜電動車「一換一」寬減將成絕唱 呢日期後買 Tesla 或貴逾 XX 萬 專家：呢部分電動車受影響最大",
      "link": "https://ezone.hk/article/20090116/%E8%B2%A1%E6%94%BF%E9%A0%90%E7%AE%97%E6%A1%882026-%E9%9B%BB%E5%8B%95%E8%BB%8A-%E4%B8%80%E6%8F%9B%E4%B8%80-%E5%AF%AC%E6%B8%9B%E5%B0%87%E6%88%90%E7%B5%95%E5%94%B1-%E5%91%A2%E6%97%A5%E6%9C%9F%E5%BE%8C%E8%B2%B7-Tesla-%E6%88%96%E8%B2%B4%E9%80%BE-XX-%E8%90%AC-%E5%B0%88%E5%AE%B6-%E5%91%A2%E9%83%A8%E5%88%86%E9%9B%BB%E5%8B%95%E8%BB%8A%E5%8F%97%E5%BD%B1%E9%9F%BF%E6%9C%80%E5%A4%A7",
      "source": "E-zone",
      "category": "科技",
      "scraped_at": "2026-02-26 14:44:15"
    },
    {
      "title": "財政預算案2026｜本港交通智能化　推行無人機應用航線　年內啟用自動駕駛「航天走廊」",
      "link": "https://ezone.hk/article/20090108/%E8%B2%A1%E6%94%BF%E9%A0%90%E7%AE%97%E6%A1%882026-%E6%9C%AC%E6%B8%AF%E4%BA%A4%E9%80%9A%E6%99%BA%E8%83%BD%E5%8C%96-%E6%8E%A8%E8%A1%8C%E7%84%A1%E4%BA%BA%E6%A9%9F%E6%87%89%E7%94%A8%E8%88%AA%E7%B7%9A-%E5%B9%B4%E5%85%A7%E5%95%9F%E7%94%A8%E8%87%AA%E5%8B%95%E9%A7%95%E9%A7%9B-%E8%88%AA%E5%A4%A9%E8%B5%B0%E5%BB%8A",
      "source": "E-zone",
      "category": "科技",
      "scraped_at": "2026-02-26 14:44:15"
    },
    {
      "title": "Xiaomi 17 Ultra 搭載 LOFIC 技術巔峰 2 月 28 日國際版發布吳彥祖擔任體驗官",
      "link": "https://ezone.hk/article/20090082/Xiaomi-17-Ultra-%E6%90%AD%E8%BC%89-LOFIC-%E6%8A%80%E8%A1%93%E5%B7%94%E5%B3%B0-2-%E6%9C%88-28-%E6%97%A5%E5%9C%8B%E9%9A%9B%E7%89%88%E7%99%BC%E5%B8%83%E5%90%B3%E5%BD%A5%E7%A5%96%E6%93%94%E4%BB%BB%E9%AB%94%E9%A9%97%E5%AE%98",
      "source": "E-zone",
      "category": "科技",
      "scraped_at": "2026-02-26 14:44:15"
    },
    {
      "title": "2026 財政預算案 政府撥 5,000 萬推全民 AI 培訓 即睇20 億「優質教育基金」3 大用途",
      "link": "https://ezone.hk/article/20090097/2026-%E8%B2%A1%E6%94%BF%E9%A0%90%E7%AE%97%E6%A1%88-%E6%94%BF%E5%BA%9C%E6%92%A5-5-000-%E8%90%AC%E6%8E%A8%E5%85%A8%E6%B0%91-AI-%E5%9F%B9%E8%A8%93-%E5%8D%B3%E7%9D%8720-%E5%84%84-%E5%84%AA%E8%B3%AA%E6%95%99%E8%82%B2%E5%9F%BA%E9%87%91-3-%E5%A4%A7%E7%94%A8%E9%80%94",
      "source": "E-zone",
      "category": "科技",
      "scraped_at": "2026-02-26 14:44:15"
    },
    {
      "title": "ROG 20週年｜ROG Nebula Display持續革新 3大產品定義電競巔峰標準",
      "link": "https://ezone.hk/article/20089671/ROG-20%E9%80%B1%E5%B9%B4-ROG-Nebula-Display%E6%8C%81%E7%BA%8C%E9%9D%A9%E6%96%B0-3%E5%A4%A7%E7%94%A2%E5%93%81%E5%AE%9A%E7%BE%A9%E9%9B%BB%E7%AB%B6%E5%B7%94%E5%B3%B0%E6%A8%99%E6%BA%96",
      "source": "E-zone",
      "category": "科技",
      "scraped_at": "2026-02-26 14:44:15"
    },
    {
      "title": "81 款耳機全含致癌物？大部分知名牌子都中！「一情況」恐加速人體吸收毒素",
      "link": "https://ezone.hk/article/20089715/81-%E6%AC%BE%E8%80%B3%E6%A9%9F%E5%85%A8%E5%90%AB%E8%87%B4%E7%99%8C%E7%89%A9-%E5%A4%A7%E9%83%A8%E5%88%86%E7%9F%A5%E5%90%8D%E7%89%8C%E5%AD%90%E9%83%BD%E4%B8%AD-%E4%B8%80%E6%83%85%E6%B3%81-%E6%81%90%E5%8A%A0%E9%80%9F%E4%BA%BA%E9%AB%94%E5%90%B8%E6%94%B6%E6%AF%92%E7%B4%A0",
      "source": "E-zone",
      "category": "科技",
      "scraped_at": "2026-02-26 14:44:15"
    },
    {
      "title": "DeepFake詐騙橫行！AI換臉「有片未為真」專家教6招識破防勒索",
      "link": "https://ezone.hk/article/20025043/DeepFake%E8%A9%90%E9%A8%99%E6%A9%AB%E8%A1%8C-AI%E6%8F%9B%E8%87%89-%E6%9C%89%E7%89%87%E6%9C%AA%E7%82%BA%E7%9C%9F-%E5%B0%88%E5%AE%B6%E6%95%996%E6%8B%9B%E8%AD%98%E7%A0%B4%E9%98%B2%E5%8B%92%E7%B4%A2",
      "source": "E-zone",
      "category": "科技",
      "scraped_at": "2026-02-26 14:44:15"
    },
    {
      "title": "【國泰航空台灣優惠】限時85折優惠！來回台北/高雄連稅1千4起！早去晚返包23kg行李",
      "link": "https://flyday.hk/cathay-pacific-taiwan-promotions",
      "source": "FlyDayhk",
      "category": "旅遊",
      "scraped_at": "2026-02-26 14:44:15"
    },
    {
      "title": "【達美航空】未復航再減至新低價！來回洛杉磯連稅4千2起！6月6起每日一班直飛洛杉磯！",
      "link": "https://flyday.hk/delta-airlines",
      "source": "FlyDayhk",
      "category": "旅遊",
      "scraped_at": "2026-02-26 14:44:15"
    },
    {
      "title": "【國泰航空日本優惠】日本線限時優惠折後來回連稅2千6起！3月29日起福岡線加班！新增早上10點出發及傍晚5點回程航班",
      "link": "https://flyday.hk/cathay-pacific-japan-promotions",
      "source": "FlyDayhk",
      "category": "旅遊",
      "scraped_at": "2026-02-26 14:44:15"
    },
    {
      "title": "【泰酷航空】開航無望？泰酷航空被吊銷航空營運許可證！原定25年首航包括香港、上海、東京及新加坡！",
      "link": "https://flyday.hk/really-cool-airlines",
      "source": "FlyDayhk",
      "category": "旅遊",
      "scraped_at": "2026-02-26 14:44:15"
    },
    {
      "title": "【馬來西亞國際航空】馬年率先減！經馬航官網預訂全線機票，可享高達85折！Enrich 會員額外95折優惠！暑假出發都有優惠！",
      "link": "https://flyday.hk/malaysia-airlines-promotion-2",
      "source": "FlyDayhk",
      "category": "旅遊",
      "scraped_at": "2026-02-26 14:44:15"
    },
    {
      "title": "【國泰航空優惠】全球精選航點高達85折！曼谷、溫哥華、西雅圖、珀斯等都有份！網上訂票仲有獨家 Cathay Shop 購物優惠，精選行李箱低至4折起！",
      "link": "https://flyday.hk/cathay-pacific-special-fares-2026",
      "source": "FlyDayhk",
      "category": "旅遊",
      "scraped_at": "2026-02-26 14:44:15"
    },
    {
      "title": "【易斯達航空EastarJet韓國優惠】來回首爾連稅$1,168起！包15kg寄艙行李！每日一班，凌晨機去晚機返",
      "link": "https://flyday.hk/eastarjet-korea-promotions",
      "source": "FlyDayhk",
      "category": "旅遊",
      "scraped_at": "2026-02-26 14:44:15"
    },
    {
      "title": "Perplexity 推出 Computer 新一代通用 AI 數碼勞工較 OpenClaw 優勝",
      "link": "https://unwire.hk/2026/02/26/perplexity-computer-launched/fun-tech/?utm_source=rss&utm_medium=rss&utm_campaign=perplexity-computer-launched",
      "source": "Unwire.hk",
      "category": "科技",
      "scraped_at": "2026-02-26 14:44:16"
    },
    {
      "title": "年度防詐報告揭 8 成訊息騙案屬貸款陷阱 假冒銀行通知急增",
      "link": "https://unwire.hk/2026/02/26/2025-scam-report-hong-kong-data-leak/software/?utm_source=rss&utm_medium=rss&utm_campaign=2025-scam-report-hong-kong-data-leak",
      "source": "Unwire.hk",
      "category": "科技",
      "scraped_at": "2026-02-26 14:44:16"
    },
    {
      "title": "Elon Musk 嫌 Grok 答錯《柏德之門》   押後模型更新並緊急抽調工程師補救",
      "link": "https://unwire.hk/2026/02/26/musk-grok-baldurs-gate-update-delay/game-channel/?utm_source=rss&utm_medium=rss&utm_campaign=musk-grok-baldurs-gate-update-delay",
      "source": "Unwire.hk",
      "category": "科技",
      "scraped_at": "2026-02-26 14:44:16"
    },
    {
      "title": "【評測】Samsung Buds4 系列快速評測\t金屬感更重 + 低音表現更佳",
      "link": "https://unwire.hk/2026/02/26/samsung-galaxybuds4-quick-review/mobile-music/headphones/?utm_source=rss&utm_medium=rss&utm_campaign=samsung-galaxybuds4-quick-review",
      "source": "Unwire.hk",
      "category": "科技",
      "scraped_at": "2026-02-26 14:44:16"
    },
    {
      "title": "【評測】Samsung Galaxy S26 系列快速評測\t「靠把口」操作 AI + 防偷窺熒幕更實用",
      "link": "https://unwire.hk/2026/02/26/samsung-galaxys26-quick-review/review-2/?utm_source=rss&utm_medium=rss&utm_campaign=samsung-galaxys26-quick-review",
      "source": "Unwire.hk",
      "category": "科技",
      "scraped_at": "2026-02-26 14:44:16"
    },
    {
      "title": "旺角學生公寓尿袋過熱起火8人送院  部份人面部熏黑   尿袋安全注意事項",
      "link": "https://unwire.hk/2026/02/25/mong-kok-student-apartment-power-bank-fire/mobile-phone/phone-parts/?utm_source=rss&utm_medium=rss&utm_campaign=mong-kok-student-apartment-power-bank-fire",
      "source": "Unwire.hk",
      "category": "科技",
      "scraped_at": "2026-02-26 14:44:16"
    },
    {
      "title": "PayMe 收「過錯」款項  直接退款「太天真」？  PayMe 官方提供解決途徑",
      "link": "https://unwire.hk/2026/02/25/payme-wrong-transfer-scam-risk-hkma-guide/tech-secure/?utm_source=rss&utm_medium=rss&utm_campaign=payme-wrong-transfer-scam-risk-hkma-guide",
      "source": "Unwire.hk",
      "category": "科技",
      "scraped_at": "2026-02-26 14:44:16"
    },
    {
      "title": "Logitech G PRO X2 SUPERSTRIKE 電競滑鼠實試   61g 超輕量、超靜音、電感式類比開關手感佳",
      "link": "https://unwire.hk/2026/02/25/logitech-g-pro-x2-superstrike-review/notebook/?utm_source=rss&utm_medium=rss&utm_campaign=logitech-g-pro-x2-superstrike-review",
      "source": "Unwire.hk",
      "category": "科技",
      "scraped_at": "2026-02-26 14:44:16"
    },
    {
      "title": "固網電話地位式微  官方數據指 52.6% 台灣人  在家都只用流動電話",
      "link": "https://unwire.hk/2026/02/25/taiwan-landline-decline-ncc-survey-2025/mobile-phone/?utm_source=rss&utm_medium=rss&utm_campaign=taiwan-landline-decline-ncc-survey-2025",
      "source": "Unwire.hk",
      "category": "科技",
      "scraped_at": "2026-02-26 14:44:16"
    },
    {
      "title": "中國湖北推空中的士   飛行時間超 20 分鐘, 可坐 4 人  兼具載人與運貨功能",
      "link": "https://unwire.hk/2026/02/25/hubei-evtol-flying-car-v1000-2026/fun-tech/?utm_source=rss&utm_medium=rss&utm_campaign=hubei-evtol-flying-car-v1000-2026",
      "source": "Unwire.hk",
      "category": "科技",
      "scraped_at": "2026-02-26 14:44:16"
    }
  ]
}